nitegame/__init__.py
nitegame/codekit.py
nitegame/core.py
nitegame/draw.py
nitegame/features.py
nitegame/locals.py
nitegame-0.0.53.dist-info/LICENSE
nitegame-0.0.53.dist-info/METADATA
nitegame-0.0.53.dist-info/WHEEL
nitegame-0.0.53.dist-info/top_level.txt
nitegame-0.0.53.dist-info/RECORD
