Metadata-Version: 2.1
Name: nitegame
Version: 0.0.53
Summary: A game engine built on Pygame & ModernGL meant to simplify common game systems, and the process of developing, primarily, 2D games.
Author-email: Zachery Visger <niteboundx@gmail.com>
License: MIT License
Project-URL: Homepage, https://github.com/Nitebound/Nitegame-Engine
Keywords: games,tools,engine
Classifier: License :: OSI Approved :: MIT License
Classifier: Programming Language :: Python
Classifier: Programming Language :: Python :: 3
Requires-Python: >=3.9
License-File: LICENSE
Requires-Dist: pygame
Requires-Dist: numpy
Requires-Dist: noise
Requires-Dist: pillow
Requires-Dist: PyOpenGL
Requires-Dist: PyOpenGL-accelerate
